blam_sdk/__init__.py
blam_sdk/sdk_config.py
blam_sdk/agent_core/__init__.py
blam_sdk/agent_core/agent.py
blam_sdk/agent_core/agent_conf.py
blam_sdk/agent_core/base_action_handler.py
blam_sdk/agent_core/log_config.py
blam_sdk/agent_core/resources/agent.schema.yml
blam_sdk/services/__init__.py
blam_sdk/services/action_service.py
blam_sdk/services/asset_service.py
blam_sdk/services/base_service.py
blam_sdk/services/connections_service.py
blam_sdk/services/iam_service.py
blam_sdk/services/storage_service.py
blam_sdk/utils/__init__.py
blam_sdk/utils/asset_storage_helper.py
blam_sdk-0.0.6.dist-info/METADATA
blam_sdk-0.0.6.dist-info/WHEEL
blam_sdk-0.0.6.dist-info/top_level.txt
blam_sdk-0.0.6.dist-info/RECORD
